[
  {
    "overall": 5,
    "career": 4,
    "balance": 4,
    "compensation": 3,
    "culture": 5,
    "management": 4,
    "summary": "Great work life balance ",
    "pros": "Supportive team culture, excellent work-life balance, and strong leadership guidance. Resources and training are abundant, helping employees grow technically and professionally. The onboarding program is also well-structured and empowering.",
    "cons": "Amazon’s fast-paced environment can be overwhelming at times. Navigating internal tools and processes may require time and patience, especially for newcomers.",
    "reasonResign": null,
    "createdAt": "2025-05-07T01:59:15.000Z"
  },
  {
    "overall": 4,
    "career": 5,
    "balance": 3,
    "compensation": 5,
    "culture": 4,
    "management": 4,
    "summary": "High stake high reward ",
    "pros": "Come build your muscle as a software engineer - lots of learn everyday ",
    "cons": "The pros come at the cost of compromising work-life balance ",
    "reasonResign": null,
    "createdAt": "2025-05-07T00:12:47.000Z"
  },
  {
    "overall": 2,
    "career": 4,
    "balance": 1,
    "compensation": 3,
    "culture": 1,
    "management": 1,
    "summary": "Bad work life balance",
    "pros": "Cool projects to work on. You can learn a lot ",
    "cons": "Bad work life balance . Incompetent and micro managing managers\n",
    "reasonResign": null,
    "createdAt": "2025-05-06T22:21:52.000Z"
  },
  {
    "overall": 4,
    "career": 4,
    "balance": 3,
    "compensation": 3,
    "culture": 3,
    "management": 4,
    "summary": "Working with smart people and growth",
    "pros": "Working with smart people and good career growth. Would recommend to someone who needs career growth\n",
    "cons": "Too many projects at a time which leads to too many meetings affecting work life balance \n\n",
    "reasonResign": null,
    "createdAt": "2025-05-06T18:52:02.000Z"
  },
  {
    "overall": 5,
    "career": 5,
    "balance": 5,
    "compensation": 5,
    "culture": 5,
    "management": 3,
    "summary": "It’s fine ",
    "pros": "Pays well and pretty solid company that has a lot\nOf interesting things going on and \n\n\n",
    "cons": "Bad management and a lot of politics that can affect enjoying your jobs ",
    "reasonResign": null,
    "createdAt": "2025-05-06T18:46:35.000Z"
  },
  {
    "overall": 5,
    "career": 5,
    "balance": 5,
    "compensation": 5,
    "culture": 5,
    "management": 5,
    "summary": "Great work life balance",
    "pros": "There are great people to work with, great perks, and some interesting problems.",
    "cons": "sometimes there’s a lot of red tape due to size",
    "reasonResign": null,
    "createdAt": "2025-05-06T17:14:28.000Z"
  },
  {
    "overall": 3,
    "career": 3,
    "balance": 3,
    "compensation": 3,
    "culture": 2,
    "management": 2,
    "summary": "No linger what it was",
    "pros": "Challenging probs to solve . Access to latest AI models via AWS",
    "cons": "Many orga are directionless , L8 leaders in most orga are cluless or have ni strategy , resulting in constant org changes , no stability and no differentiation of talent",
    "reasonResign": null,
    "createdAt": "2025-05-06T13:53:08.000Z"
  },
  {
    "overall": 1,
    "career": 3,
    "balance": 1,
    "compensation": 4,
    "culture": 1,
    "management": 1,
    "summary": "Toxic",
    "pros": "The pay is good for the most part. Decent benefits.",
    "cons": "You will have no life and you will be miserable ",
    "reasonResign": null,
    "createdAt": "2025-05-06T04:40:21.000Z"
  },
  {
    "overall": 3,
    "career": 2,
    "balance": 2,
    "compensation": 1,
    "culture": 1,
    "management": 2,
    "summary": "Entirely org and leader dependent. ",
    "pros": "Have worked with some really smart people and had a few great managers ",
    "cons": "Some organizations reward the wrong type of behavior and turn south very quickly ",
    "reasonResign": null,
    "createdAt": "2025-05-06T02:57:11.000Z"
  },
  {
    "overall": 4,
    "career": 3,
    "balance": 5,
    "compensation": 3,
    "culture": 4,
    "management": 3,
    "summary": "Customer Facing engineering is more chill",
    "pros": "Flexible work hours and good work life balance\nNo micro management \nGood variety of work with the customers ",
    "cons": "Bad leadership and short-sighted decision making\nBenefits and pay is super mid\nCareer progression in ProServe org is too bureaucratic and painful ",
    "reasonResign": null,
    "createdAt": "2025-05-05T23:19:08.000Z"
  },
  {
    "overall": 4,
    "career": 5,
    "balance": 5,
    "compensation": 4,
    "culture": 4,
    "management": 4,
    "summary": "Amazon",
    "pros": "In good role with good visibility to continue to grow personally ",
    "cons": "Growth and think big is non existent now since 2022",
    "reasonResign": null,
    "createdAt": "2025-05-05T19:32:17.000Z"
  },
  {
    "overall": 2,
    "career": 2,
    "balance": 1,
    "compensation": 4,
    "culture": 2,
    "management": 1,
    "summary": "Good pay. No Life",
    "pros": "External recognition for Faang. Makes you feel good about it. ",
    "cons": "Overworked. Long hours and not satisfying work. Need your manager’s blessing to grow. \n",
    "reasonResign": null,
    "createdAt": "2025-05-05T17:23:21.000Z"
  },
  {
    "overall": 4,
    "career": 3,
    "balance": 2,
    "compensation": 3,
    "culture": 3,
    "management": 3,
    "summary": "Good company to start your career",
    "pros": "- A lot to learn from different people and gain different experiences",
    "cons": "- Role guidelines are subjective and are vaguely followed\n- Pay scale for non tech classified roles are not even sustainable and they expect tech skills\n- growth is directly proportional to your manager and your leadership. If they feel like then only you will get promoted",
    "reasonResign": null,
    "createdAt": "2025-05-05T03:40:19.000Z"
  },
  {
    "overall": 3,
    "career": 4,
    "balance": 2,
    "compensation": 5,
    "culture": 2,
    "management": 3,
    "summary": "Career path dependent on your manager  ",
    "pros": "Great place to learn with a lot of good processes",
    "cons": "Your experience and career growth is largely dependent on your manager",
    "reasonResign": null,
    "createdAt": "2025-05-05T02:31:42.000Z"
  },
  {
    "overall": 2,
    "career": 3,
    "balance": 2,
    "compensation": 4,
    "culture": 2,
    "management": 2,
    "summary": "Bad work life balance ",
    "pros": "Only made for workoholics with no life outside work. They give you opportunity to work on as many projects as you want.",
    "cons": "Burn out and Return to Office with badge monitoring. Bad culture\n",
    "reasonResign": null,
    "createdAt": "2025-05-04T23:05:20.000Z"
  },
  {
    "overall": 4,
    "career": 2,
    "balance": 3,
    "compensation": 3,
    "culture": 3,
    "management": 3,
    "summary": "Megacorporation and megapolitics",
    "pros": "If you are smart and thrive with conflict and politics you can work on a scale unlike any other.",
    "cons": "So much politics, horrible talent review process, so big and corporate that you're never going to feel human working there.",
    "reasonResign": null,
    "createdAt": "2025-05-04T21:45:21.000Z"
  },
  {
    "overall": 3,
    "career": 3,
    "balance": 1,
    "compensation": 4,
    "culture": 2,
    "management": 3,
    "summary": "Wlb is bad. Good place if you want to slog and grow",
    "pros": "Compensation was good, interesting projects and possibility of growth. Team members are good.",
    "cons": "Work life balance is a mess. Product and other teams are non existent. Tech does everything so is responsible for everything including the chaos.",
    "reasonResign": null,
    "createdAt": "2025-05-04T21:16:59.000Z"
  },
  {
    "overall": 4,
    "career": 5,
    "balance": 3,
    "compensation": 4,
    "culture": 4,
    "management": 3,
    "summary": "Mediocre work life balance, but you can learn a lot",
    "pros": "Many talented people to get to know. You will learn not only skills but how to organize your work etc.",
    "cons": "Mediocre work life balance and micromanagement (you need to close certain amount of tickets during a sprint)",
    "reasonResign": null,
    "createdAt": "2025-05-04T21:03:44.000Z"
  },
  {
    "overall": 1,
    "career": 2,
    "balance": 3,
    "compensation": 4,
    "culture": 1,
    "management": 2,
    "summary": "Avoid if you have self-respect",
    "pros": "- talented people\n- decent pay\n- looks good on resume",
    "cons": "It’s Amazon… there’s already enough negative reviews out there. Just read one of those because they are mostly true.",
    "reasonResign": null,
    "createdAt": "2025-05-04T20:45:52.000Z"
  },
  {
    "overall": 3,
    "career": 3,
    "balance": 3,
    "compensation": 3,
    "culture": 3,
    "management": 3,
    "summary": "Interesting work, smart people, have to navigate politics as expected in a large org",
    "pros": "Scale of work is great, lots of learning, easy to move internally ",
    "cons": "Many stakeholders, bias for action valued over strategy, lots of churn ",
    "reasonResign": null,
    "createdAt": "2025-05-04T04:12:15.000Z"
  },
  {
    "overall": 2,
    "career": 3,
    "balance": 1,
    "compensation": 3,
    "culture": 1,
    "management": 2,
    "summary": "Internal politics hellhole",
    "pros": "You learn a lot. Many SDEs are good, lots of scope to change teams during your initial years. ",
    "cons": "You have to fight to again visibility, no matter how talented your are you need to kiss management’s a..\n\nLot of internal re-orgs and internal teams trying to cannibalize your service is common. \n\nManger will leave left and right you need to fight for your promo.  ",
    "reasonResign": null,
    "createdAt": "2025-05-03T21:19:28.000Z"
  },
  {
    "overall": 2,
    "career": 3,
    "balance": 2,
    "compensation": 3,
    "culture": 1,
    "management": 1,
    "summary": "Bad management ",
    "pros": "A lot of internal tools and computing resources. There are some smart folks and the products are well known \n",
    "cons": "A lot of politics and micromanagement, many reshuffle and many small reorg ",
    "reasonResign": null,
    "createdAt": "2025-05-03T16:50:09.000Z"
  },
  {
    "overall": 3,
    "career": 3,
    "balance": 2,
    "compensation": 1,
    "culture": 1,
    "management": 1,
    "summary": "Avoid it at all costs unless you’re desperate ",
    "pros": "Don’t join unless you’re desperate. \nThe only thing that may benefit you is the “big”name stamp on your resume. \n",
    "cons": "Tenure-based instead of merit-based promotions. \nReorgs every month every quarter every year. \nNo vision from leadership. \n5-day RTO. \nBackstabbing peer reviews.\n\n\n",
    "reasonResign": null,
    "createdAt": "2025-05-03T03:45:37.000Z"
  },
  {
    "overall": 2,
    "career": 3,
    "balance": 1,
    "compensation": 3,
    "culture": 3,
    "management": 2,
    "summary": "Good for a sprint, not suitable for marathons.",
    "pros": "1. A high-paced environment, provides quick learning opportunities.\n2. Decent overall compensation.\n3. Jack of all trades, master of none or maybe one.",
    "cons": "1. Little respect for boundaries.\n2. All work and no play makes Jack a dull boy.\n3. Exhaustive enough to prevent you from preparing for a switch.\n4. Incapable and opaque managers - L7-L8.\n5. Compensation/amount of work done very poor.\n6. No extra benefits than compensation whatsoever.",
    "reasonResign": null,
    "createdAt": "2025-05-02T23:29:53.000Z"
  },
  {
    "overall": 4,
    "career": 5,
    "balance": 2,
    "compensation": 3,
    "culture": 3,
    "management": 5,
    "summary": "Amazing if you have a great team and manager",
    "pros": "Lots of room to grow and learn. Many exciting projects.",
    "cons": "Constant re-orgs and politics make it difficult to actually make an impact. ",
    "reasonResign": null,
    "createdAt": "2025-05-02T19:26:00.000Z"
  },
  {
    "overall": 4,
    "career": 3,
    "balance": 4,
    "compensation": 5,
    "culture": 3,
    "management": 5,
    "summary": "Good wlb",
    "pros": "Smart colleagues and management. Good problems to solve. Growth opportunities",
    "cons": "Complicated tech slows down development and release of new features",
    "reasonResign": null,
    "createdAt": "2025-05-02T19:17:54.000Z"
  },
  {
    "overall": 2,
    "career": 2,
    "balance": 1,
    "compensation": 3,
    "culture": 2,
    "management": 1,
    "summary": "Diminishing returns",
    "pros": "Pay is there and you get AMZN stock\nYou can get to work on some cool projects at AWS\nLiterally anyone will riff with you about this bs \nHealthcare and insurance is adequate for cost\nYou can get an org with a lot of smart people",
    "cons": "RTO5\nBenefits seem to be disappearing \nPay is diminishing based on bs\nOncall will give you PTSD like Vietnam \nYou can get stuck working on initiatives that no one thought about giving you brain cancer in the process\nAttrition and brain drain is real\nPIP exists although I have never personally seen it, it feels like existential dread\nDocumentation hell exists\nManagement hell exists ",
    "reasonResign": null,
    "createdAt": "2025-05-02T17:58:43.000Z"
  },
  {
    "overall": 3,
    "career": 2,
    "balance": 2,
    "compensation": 4,
    "culture": 2,
    "management": 2,
    "summary": "Not the best WLB, but a good place to learn",
    "pros": "- Great exposure to big scale problems\n- Great opportunities to learn esp as a new grad ",
    "cons": "- No dedicated new grad program\n- Practically non existent benefits or perks ",
    "reasonResign": null,
    "createdAt": "2025-05-02T17:12:36.000Z"
  },
  {
    "overall": 2,
    "career": 3,
    "balance": 1,
    "compensation": 4,
    "culture": 2,
    "management": 3,
    "summary": "Large scale problem solving",
    "pros": "Be an expert AWS master with actual usages.\nLearn that you are filled with people dummer than you.",
    "cons": "Horrible documentation \nHorrible code quality requirement\n\n\nOverall the shop is filled with automated systems that have no understanding what needs to be done.\n\nBe ready to work with having no ownership in pride in making stuff.\n\nSlowest process in doing things.  Waterfall development pretending as Agile continuous development.  \n\n",
    "reasonResign": null,
    "createdAt": "2025-05-02T16:38:34.000Z"
  },
  {
    "overall": 4,
    "career": 2,
    "balance": 1,
    "compensation": 4,
    "culture": 3,
    "management": 3,
    "summary": "Not what it used to be",
    "pros": "Cool projects, to work on with awesome team mates but limited growth ",
    "cons": "Culture stinks and limited growth opportunities do two years and bounce \n",
    "reasonResign": null,
    "createdAt": "2025-05-02T12:18:33.000Z"
  }
]